crossauth_backend/__init__.py
crossauth_backend/auth.py
crossauth_backend/cookieauth.py
crossauth_backend/crypto.py
crossauth_backend/session.py
crossauth_backend/storage.py
crossauth_backend/utils.py
crossauth_backend/common/__init__.py
crossauth_backend/common/error.py
crossauth_backend/common/interfaces.py
crossauth_backend/common/jwt.py
crossauth_backend/common/logger.py
crossauth_backend/oauth/__init__.py
crossauth_backend/oauth/client.py
crossauth_backend/oauth/clientmanager.py
crossauth_backend/oauth/resserver.py
crossauth_backend/oauth/tokenconsumer.py
crossauth_backend/oauth/wellknown.py
crossauth_backend/storageimpl/__init__.py
crossauth_backend/storageimpl/inmemorystorage.py
crossauth_backend/storageimpl/sqlalchemystorage.py
crossauth_fastapi/__init__.py
crossauth_fastapi/fastapioauthclient.py
crossauth_fastapi/fastapiresserver.py
crossauth_fastapi/fastapiserver.py
crossauth_fastapi/fastapiserverbase.py
crossauth_fastapi/fastapisession.py
crossauth_fastapi/fastapisessionadapter.py
pycrossauth-1.0.0.dist-info/licenses/LICENSE
pycrossauth-1.0.0.dist-info/licenses/NOTICE
pycrossauth-1.0.0.dist-info/METADATA
pycrossauth-1.0.0.dist-info/WHEEL
pycrossauth-1.0.0.dist-info/top_level.txt
pycrossauth-1.0.0.dist-info/RECORD
