Metadata-Version: 2.4
Name: pycrossauth
Version: 1.0.0
Summary: Cross platform web authentication and OAuth framework
Author-email: Matthew Baker <matt@mattbaker.ch>
License: 
Project-URL: repository, https://github.com/mbakereth/crossauthjs
Project-URL: documentation, https://mattbaker.ch/pycrossauth/
Keywords: feed,reader,tutorial
Classifier: License :: OSI Approved :: Apache Software License
Classifier: Programming Language :: Python
Classifier: Programming Language :: Python :: 3
Requires-Python: >=3.12
License-File: LICENSE
License-File: NOTICE
Requires-Dist: bumpver
Requires-Dist: nulltype>=2.3.1
Requires-Dist: requests
Requires-Dist: aiohttp
Requires-Dist: pycryptodome
Requires-Dist: psycopg
Requires-Dist: psycopg_pool
Requires-Dist: sqlalchemy[asyncio]
Requires-Dist: jwt
Requires-Dist: Jinja2
Requires-Dist: qrcode[pil]
Requires-Dist: types-qrcode
Provides-Extra: build
Requires-Dist: build; extra == "build"
Requires-Dist: twine; extra == "build"
Provides-Extra: dev
Requires-Dist: dotenv-cli; extra == "dev"
Requires-Dist: sphinx; extra == "dev"
Requires-Dist: sphinx_rtd_theme; extra == "dev"
Requires-Dist: myst-parser; extra == "dev"
Requires-Dist: aioresponses; extra == "dev"
Requires-Dist: bumpver; extra == "dev"
Requires-Dist: build; extra == "dev"
Requires-Dist: twine; extra == "dev"
Provides-Extra: optional
Requires-Dist: asyncpg; extra == "optional"
Requires-Dist: fastapi[standard]; extra == "optional"
Dynamic: license-file
